bilibili_toolman/__init__.py
bilibili_toolman/__main__.py
bilibili_toolman/bilisession/__init__.py
bilibili_toolman/bilisession/client.py
bilibili_toolman/bilisession/web.py
bilibili_toolman/bilisession/common/__init__.py
bilibili_toolman/bilisession/common/submission.py
bilibili_toolman/cli/__init__.py
bilibili_toolman/cli/main.py
bilibili_toolman/cli/precentage_progress.py
bilibili_toolman/providers/__init__.py
bilibili_toolman/providers/localfile.py
bilibili_toolman/providers/youtube.py
bilibili_toolman2022-1.0.6.10.dist-info/LICENSE
bilibili_toolman2022-1.0.6.10.dist-info/METADATA
bilibili_toolman2022-1.0.6.10.dist-info/WHEEL
bilibili_toolman2022-1.0.6.10.dist-info/top_level.txt
bilibili_toolman2022-1.0.6.10.dist-info/RECORD
