Metadata-Version: 2.1
Name: bilibili-toolman2022
Version: 1.0.6.10
Summary: bilibili-toolman 哔哩哔哩搬运工具
Home-page: https://github.com/redy112/bilibilitoolman2022
Author: greats3an
Author-email: greats3an@gmail.com
License: UNKNOWN
Platform: UNKNOWN
Classifier: Programming Language :: Python :: 3
Classifier: License :: OSI Approved :: Apache Software License
Classifier: Operating System :: OS Independent
Requires-Python: >=3.6
License-File: LICENSE
Requires-Dist: requests
Requires-Dist: pycryptodome
Requires-Dist: coloredlogs
Requires-Dist: yt-dlp
Requires-Dist: tqdm
